{
  "name": "rustworkx",
  "domain": "qc",
  "discipline": "qc",
  "ecosystem": "frame",
  "collected_at": "2026-07-05T20:42:30Z",
  "errors": {},
  "github": {
    "owner": "Qiskit",
    "repo": "rustworkx",
    "errors": {},
    "full_name": "Qiskit/rustworkx",
    "description": "A high performance Python graph library implemented in Rust.",
    "homepage": "https://www.rustworkx.org",
    "default_branch": "main",
    "archived": false,
    "pushed_at": "2026-07-05T04:13:25Z",
    "stars": 1719,
    "topics": [
      "dag",
      "graph",
      "graph-theory",
      "python",
      "rust"
    ],
    "license": "Apache-2.0",
    "latest_release": {
      "tag": "0.18.0",
      "name": "0.18.0",
      "published_at": "2026-06-18T03:51:10Z"
    },
    "release_state": "release",
    "files": {
      "SECURITY.md": "# Security Policy\n\n## Supported Versions\n\nRustworkx supports one minor version release at a time both for bug and\nsecurity fixes. For example, if the most recent release is 0.12.1 the 0.12.x\nrelease series is currently supported.\n\n## Reporting a Vulnerability\n\nTo report vulnerabilities you can privately report a potential security issue\nvia the Github security vulnerabilities feature. This can be done here:\n\nhttps://github.com/Qiskit/rustworkx/security/advisories\n\nPlease do **not** open a public issue about a potential security vulnerability.\n\nYou can find more details on the security vulnerability feature in the Github\ndocumentation here:\n\nhttps://docs.github.com/en/code-security/security-advisories/guidance-on-reporting-and-writing/privately-reporting-a-security-vulnerability\n",
      "README.md": "# rustworkx\n\n[![License](https://img.shields.io/github/license/Qiskit/rustworkx.svg?style=popout-square)](https://opensource.org/licenses/Apache-2.0)\n![Build Status](https://github.com/Qiskit/rustworkx/actions/workflows/main.yml/badge.svg?branch=main)\n[![Build Status](https://img.shields.io/travis/com/Qiskit/rustworkx/main.svg?style=popout-square)](https://travis-ci.com/Qiskit/rustworkx)\n[![](https://img.shields.io/github/release/Qiskit/rustworkx.svg?style=popout-square)](https://github.com/Qiskit/rustworkx/releases)\n[![](https://img.shields.io/pypi/dm/rustworkx.svg?style=popout-square)](https://pypi.org/project/rustworkx/)\n[![Coverage Status](https://coveralls.io/repos/github/Qiskit/rustworkx/badge.svg?branch=main)](https://coveralls.io/github/Qiskit/rustworkx?branch=main)\n[![Minimum rustc 1.85](https://img.shields.io/badge/rustc-1.85+-blue.svg)](https://rust-lang.github.io/rfcs/2495-min-rust-version.html)\n[![DOI](https://joss.theoj.org/papers/10.21105/joss.03968/status.svg)](https://doi.org/10.21105/joss.03968)\n[![arXiv](https://img.shields.io/badge/arXiv-2110.15221-b31b1b.svg)](https://arxiv.org/abs/2110.15221)\n[![Zenodo](https://img.shields.io/badge/Zenodo-10.5281%2Fzenodo.5879859-blue)](https://doi.org/10.5281/zenodo.5879859)\n\n  - You can see the full rendered docs at:\n    <https://www.rustworkx.org/>\n\nA high-performance, general-purpose graph library for Python, written in Rust.\n\n## Usage\n\nOnce installed, simply import `rustworkx`.\nAll graph classes and top-level functions are accessible with a single import.\nTo illustrate this, the following example calculates the shortest path\nbetween two nodes `A` and `C` in an undirected graph.\n\n```python3\nimport rustworkx\n\n# Rustworkx's undirected graph type.\ngraph = rustworkx.PyGraph()\n\n# Each time add node is called, it returns a new node index\na = graph.add_node(\"A\")\nb = graph.add_node(\"B\")\nc = graph.add_node(\"C\")\n\n# add_edges_from takes tuples of node indices and weights,\n# and returns edge indices\ngraph.add_edges_from([(a, b, 1.5), (a, c, 5.0), (b, c, 2.5)])\n\n# Returns the path A -> B -> C\nrustworkx.dijkstra_shortest_paths(graph, a, c, weight_fn=float)\n```\n\n## Installing rustworkx\n\nrustworkx is published on [PyPI](https://pypi.org/project/rustworkx/) so on x86\\_64, i686, ppc64le, s390x, and\naarch64 Linux systems, x86\\_64 on Mac OSX, and 32 and 64 bit Windows\ninstalling is as simple as running:\n\n```bash\npip install rustworkx\n```\n\nThis will install a precompiled version of rustworkx into your Python\nenvironment.\n\n### Installing on a platform without precompiled binaries\n\nIf there are no precompiled binaries published for your system you'll have to\nbuild the package from source. However, to be able to build the package\nfrom the published source package you need to have Rust >= 1.85 installed (and\nalso [cargo](https://doc.rust-lang.org/cargo/) which is normally included with\nrust) You can use [rustup](https://rustup.rs/) (a cross platform installer for\nrust) to make this simpler, or rely on\n[other installation methods](https://forge.rust-lang.org/infra/other-installation-methods.html).\nA source package is also published on pypi, so you still can also run the above\n`pip` command to install it. Once you have rust properly installed, running:\n\n```bash\npip install rustworkx\n```\n\nwill build rustworkx for your local system from the source package and install\nit just as it would if there was a prebuilt binary available.\n\n> [!NOTE]  \n> To build from source you will need to ensure you have pip >=19.0.0\ninstalled, which supports PEP-517, or that you have manually installed\n`maturin>=1.9` prior to running `pip install rustworkx`. If you receive an\nerror about `maturin` not being found you should upgrade pip with\n`pip install -U pip` or manually install `maturin` with\n`pip install -U maturin>=1.9` and try again.\n\n### Optional dependencies\n\nIf you're planning to use the `rustworkx.visualization` module you will need to\ninstall optional dependencies to use the functions. The matplotlib based drawer\nfunction `rustworkx.visualization.mpl_draw` requires that the\n[matplotlib](https://matplotlib.org/) library is installed. This can be\ninstalled with `pip install matplotlib` or when you're installing rustworkx with\n`pip install 'rustworkx[mpl]'`. If you're going to use the graphviz based drawer\nfunction `rustworkx.visualization.graphviz_drawer` first you will need to install\ngraphviz, instructions for this can be found here:\nhttps://graphviz.org/download/#executable-packages. Then you\nwill need to install the [pillow](https://python-pillow.github.io/) Python library.\nThis can be done either with `pip install pillow` or when installing rustworkx\nwith `pip install 'rustworkx[graphviz]'`.\n\nIf you would like to install all the optional Python dependencies when you\ninstall rustworkx you can use `pip install 'rustworkx[all]'` to do this.\n\n### Conda Ecosystem\n\nCommunity-supported binaries are published to [conda-forge](https://anaconda.org/conda-forge/rustworkx). Although\nunofficial, they can be helpful for users of the `conda` ecosystem (including `mamba`, `micromamba`, and `pixi`). To install, simply run:\n\n```\nconda install -c conda-forge rustworkx\n```\n\n## Authors and Citation\n\nrustworkx is the work of [many people](https://github.com/Qiskit/rustworkx/graphs/contributors) who contribute\nto the project at different levels. If you use rustworkx in your research, please cite our\n[paper](https://doi.org/10.21105/joss.03968) as per the included [BibTeX file](CITATION.bib).\n\n## Community\n\nBesides Github interactions (such as opening issues) there are two locations\navailable to talk to other rustworkx users and developers. The first is a\npublic Slack channel in the Qiskit workspace,\n[#rustworkx](https://qiskit.slack.com/messages/rustworkx/). You can join the\nQiskit Slack workspace [here](http://ibm.co/joinqiskitslack). Additionally,\nthere is an IRC channel `#rustworkx` on the [OFTC IRC network](https://www.oftc.net/)\n\n## Building from source\n\nThe first step for building rustworkx from source is to clone it locally\nwith:\n\n```bash\ngit clone https://github.com/Qiskit/rustworkx.git\n```\n\nrustworkx uses [PyO3](https://github.com/pyo3/pyo3) and\n[maturin](https://github.com/PyO3/maturin) to build the\npython interface, which enables using standard python tooling to work. So,\nassuming you have rust installed, you can easily install rustworkx into your\npython environment using `pip`. Once you have a local clone of the repo, change\nyour current working directory to the root of the repo. Then, you can install\nrustworkx into your python env with:\n\n```bash\npip install .\n```\n\nAssuming your current working directory is still the root of the repo.\nOtherwise you can run:\n\n```bash\npip install $PATH_TO_REPO_ROOT\n```\n\nwhich will install it the same way. Then rustworkx is installed in your\nlocal python environment. There are 2 things to note when doing this\nthough, first if you try to run python from the repo root using this\nmethod it will not work as you expect. There is a name conflict in the\nrepo root because of the local python package shim used in building the\npackage. Simply run your python scripts or programs using rustworkx\noutside of the repo root. The second issue is that any local changes you\nmake to the rust code will not be reflected live in your python environment,\nyou'll need to recompile rustworkx by rerunning `pip install` to have any\nchanges reflected in your python environment.\n\n### Develop Mode\n\nIf you'd like to build rustworkx in debug mode and use an interactive debugger\nwhile working on a change you can run `maturin build --profile dev` to build rustworkx\nand then install the wheel with `pip`.\nThis will build rustworkx without optimizations and include debuginfo\nwhen running `pip install`. That can be handy for debugging.\n\n> [!TIP]\n> It's worth noting that `pip install -e` does not work, as it will link the python\npackaging shim to your python environment but not build the rustworkx binary.\n\n## Project history\n\nRustworkx was originally called retworkx and was created initially to be\na replacement for [Qiskit](https://www.ibm.com/quantum/qiskit)'s previous (and current)\nNetworkX usage (hence the original name).  The project was originally started\nto build a faster directed graph to use as the underlying data structure for\nthe DAG at the center of\n[qiskit](https://github.com/Qiskit/qiskit/)'s transpiler. However,\nsince its initial introduction the project has grown substantially and now\ncovers all applications that need to work with graphs which includes\nQiskit.\n",
      "CONTRIBUTING.md": "# Contributing\n\nFirst read the overall Qiskit project contribution guidelines. These are all\nincluded in the Qiskit documentation:\n\nhttps://github.com/Qiskit/qiskit/blob/main/CONTRIBUTING.md\n\nWhile it's not all directly applicable since most of it is about the Qiskit\nproject itself and rustworkx is an independent library developed in tandem\nwith Qiskit; the general guidelines and advice still apply here.\n\n## Contributing to rustworkx\n\nIn addition to the general guidelines there are specific details for\ncontributing to rustworkx, these are documented below.\n\n### Making changes to the code\n\nRustworkx is implemented primarily in Rust with a thin layer of Python.\nBecause of that, most of your code changes will involve modifications to\nRust files in `src`. To understand which files you need to change, we invite\nyou for an overview of our simplified source tree:\n\n```\n├── src/\n│   ├── lib.rs\n│   ├── tiny.rs\n│   ├── large/\n│   │   ├── mod.rs\n│   │   ├── pure_rust_code.rs\n│   │   └── more_pure_rust_code.rs\n```\n\n#### Module exports in `lib.rs`\n\nTo add new functions, you will need to export them in `lib.rs`. `lib.rs` will\nimport functions defined in Rust modules (see the next section), and export\nthem to Python using `m.add_wrapped(wrap_pyfunction!(your_new_function))?;`\n\n#### Adding and changing functions in modules\n\nTo add and change functions, you will need to modify module files. Modules contain pyfunctions\nthat will be exported, and can be defined either as a single file such as `tiny.rs` or as a\ndirectory with `mod.rs` such as `large/`.\n\nRust functions that are exported to Python are annotated with `#[pyfunction]`. The\nannotation gives them power to interact both with the Python interpreter and pure\nRust code. To change an existing function, search for its name and edit the code that\nalready exists.\n\nIf you want to add a new function, find the module you'd like to insert it in\nor create a new one like `your_module.rs`. Then, start with the boilerplate bellow:\n\n```rust\n/// Docstring containing description of the function\n#[pyfunction]\n#[pyo3(text_signature = \"(graph, /)\")]\npub fn your_new_function(\n    py: Python,\n    graph: &graph::PyGraph,\n) -> PyResult<()> {\n    /* Your code goes here */\n}\n```\n\n> __NOTE:__  If you create a new `your_module.rs`, remember to declare and import it in `lib.rs`:\n> ```rust\n> mod your_module;\n> use your_module::*;\n> ```\n\n#### Module directories: when a single file is not enough\n\nSometimes you will find that it is hard to organize a module in a tiny\nfile like `tiny.rs`. In those cases, we suggest moving the files to a directory\nand splitting them following the structure of `large/`.\n\nModule directories have a `mod.rs` file containing the pyfunctions. The pyfunctions\nin that file then delegate most of logic by importing and calling pure Rust code from\n`pure_rust_code.rs` and `more_pure_rust_code.rs`.\n\n> __NOTE:__ Do you still have questions about making your contribution?\n> Contact us at the [\\#rustworkx channel in Qiskit Slack](https://qiskit.slack.com/messages/rustworkx/)\n\n### rustworkx-core\n\nIf you're working on writing a pure rust function and it can be made generic\nsuch that it works for any petgraph graph (if applicable) and that it has\nno dependency on Python or pyo3, it probably makes sense in `rustworkx-core`.\n`rustworkx-core` is a standalone rust library that's used to provide a Rust API\nto both rustworkx and other rust applications or libraries. Unlike rustworkx\nit's a Rust library and not a Python library and is designed to be an add-on\nlibrary on top of petgraph that provides additional graph algorithms and\nfunctionality.\n\nWhen contributing to rustworkx-core the key differences to keep in mind are that\nthe public rust interface needs to be treated as a stable interface, which is\ndifferent from rustworkx where the stable rust interface compatibility doesn't\nmatter only the exported Python API. Additionally documentation and testing\nshould be done via cargo doc and cargo test. It is expected that any new\nfunctionality or changes to rustworkx-core is also being used by rustworkx so\ntest coverage is needed both via python in the rustworkx tests and via the\nrustworkx-core rust interface.\n\n### Tests\n\nOnce you've made a code change, it is important to verify that your change\ndoes not break any existing tests and that any new tests that you've added\nalso run successfully. Before you open a new pull request for your change,\nyou'll want to run the test suite locally.\n\nThe easiest way to run the test suite is to use\n[**Nox**](https://nox.thea.codes/en/stable/). You can install Nox\nwith pip: `pip install -U \"nox[uv]\"`. Nox provides several advantages, but the\nbiggest one is that it builds an isolated virtualenv for running tests. This\nmeans it does not pollute your system python when running. However, by default\nNox will recompile rustworkx from source every time it is run even if there\nare no changes made to the rust code. To avoid this you can use the\n`--no-install` package if you'd like to rerun tests without recompiling.\nNote, you only want to use this flag if you recently ran Nox and there are no\nrust code (or packaged python code) changes to the repo since then. Otherwise\nthe rustworkx package Nox installs in its virtualenv will be out of date (or\nmissing).\n\nNote, if you run tests outside of Nox that you can **not** run the tests from\nthe root of the repo, this is because rustworkx packaging shim will conflict\nwith imports from rustworkx the installed version of rustworkx (which contains\nthe compiled extension).\n\n#### Running tests with a specific Python version\n\nIf you want to run the tests with a specific version of Python, use the `test_with_version`\ntarget. For example, to launch a test with version 3.11 the command is:\n\n```python\nnox --python 3.11 -e test_with_version\n```\n\n#### Running subsets of tests\n\nIf you just want to run a subset of tests you can pass a selection regex to the\ntest runner. For example, if you want to run all tests that have \"dag\" in the\ntest id you can run: `nox -e test -- dag`. You can pass arguments directly to the\ntest runner after the bare `--`. To see all the options on test selection you\ncan refer to the stestr manual:\n\nhttps://stestr.readthedocs.io/en/stable/MANUAL.html#test-selection\n\nIf you want to run a single test module, test class, or individual test method\nyou can do this faster with the `-n`/`--no-discover` option. For example:\n\nto run a module:\n```\nnox -e test -- -n test_max_weight_matching\n```\nor to run the same module by path:\n```\nnox -e test -- -n graph/test_nodes.py\n```\nto run a class:\n```\nnox -e test -- -n graph.test_nodes.TestNodes\n```\nto run a method:\n```\nnox -e test -- -n graph.test_nodes.TestNodes.test_no_nodes\n```\n\nIt's important to note that Nox will be running from the `tests/` directory in\nthe repo, so any paths you pass to the test runner via path need to be relative\nto that directory.\n\n#### Visualization Tests\n\nWhen running the visualization tests, each test will generate a visualization\nand only fail if an exception is raised by the call. Each test saves the output\nimage to the current working directory (which if running tests with `nox` is\n`tests/`) to ensure the generated image is usable. However to not clutter the\nsystem each test cleans up this generated image and by default a test run does\nnot include any way to view the images from the visualization tests.\n\nIf you want to inspect the output from the visualization tests (which is common\nif you're working on visualizations) you can set the\n`RUSTWORKX_TEST_PRESERVE_IMAGES` environment variable to any value and this will\nskip the cleanup. This will enable you to look at the output image and ensure the\nvisualization is correct. For example, running:\n\n```\nRUSTWORKX_TEST_PRESERVE_IMAGES=1 nox -e test\n```\n\nwill run the visualization tests and preserve the generated image files after\nthe run finishes so you can inspect the output.\n\n#### rustworkx-core tests\n\nAs rustworkx-core is a standalone rust crate with its own public interface it\nneeds its own testing. These tests can be a combination of doc tests (embedded\ncode examples in the docstrings in the rust code) or standalone tests. You\ncan refer to the rust book on how to add tests:\n\nhttps://doc.rust-lang.org/book/ch11-01-writing-tests.html\n\nThe rustworkx-core tests can be run with:\n```\ncargo test --workspace\n```\n\n### Fuzz Testing in rustworkx\n\nWe use cargo-fuzz to test rustworkx for unexpected crashes or undefined behavior. Follow these steps to run fuzzing locally.\n\n#### Building Fuzz Targets\nTo build the fuzzing targets, first install cargo-fuzz:\n```sh\ncargo install cargo-fuzz\n```\nthen run the following command:\n\n```sh\ncargo fuzz build\n```\n#### To run a fuzz test (e.g., test_traversal_node_coverage):\n\nList all the targets:\n```sh\ncargo fuzz list\n```\nRun the tests from the list\n```sh\ncargo fuzz run test_traversal_node_coverage\n```\nFor nightly toolchain:\n```sh\ncargo +nightly fuzz run test_traversal_node_coverage\n```\nLimit fuzz testing to a specific time (e.g., 60 seconds):\n```sh\ncargo +nightly fuzz run test_traversal_node_coverage -- -max_total_time=60\n```\n#### Interpreting Failures\nFailures are stored in the fuzz/artifacts/ directory.\n\n#### Contributing to Fuzzing\n\nAdd Fuzz Targets: Create new targets in the fuzz directory.\nFix Failures: Investigate and fix bugs found by fuzz tests.\n\nFuzz tests can be resource-heavy. Run them locally to save resources.\nSubmit fuzz tests with detailed documentation and commit messages.\n\n### Style\n\n#### Rust\n\nRust is the primary language of rustworkx and all the functional code in the\nlibraries is written in Rust. The Rust code in rustworkx uses\n[rustfmt](https://github.com/rust-lang/rustfmt) to enforce consistent style.\nCI jobs are configured to ensure to check this. Luckily adapting your code is\nas simple as running:\n\n```bash\ncargo fmt\n```\n\nlocally. This will automatically restyle the rust code in rustworkx to match\nwhat CI is checking.\n\n##### Lint\n\nAn additional step is to run [clippy](https://github.com/rust-lang/rust-clippy)\non your changes. You can execute it by running:\n\n```bash\ncargo clippy\n```\n\nIf you want a more detailed feedback identical to CI, run instead:\n\n```bash\ncargo clippy --workspace --all-targets -- -D warnings\n```\n\n#### Python\n\nPython is used primarily for tests and some small pieces of packaging\nand namespace configuration code in the actual library.\n[ruff](https://github.com/astral-sh/ruff) is used to enforce consistent\nstyle in the python code in the repository. You can run them via Nox using:\n\n```bash\nnox -e lint\n```\n\nThis will also run `cargo fmt` in check mode to ensure that you ran `cargo fmt`\nand will fail if the Rust code doesn't conform to the style rules.\n\nIf ruff returns a code formatting error you can run `nox -e format` to automatically\nupdate the code formatting to conform to the style.\n\n### Building documentation\n\nJust like with tests building documentation is done via Nox. This will handle\ncompiling rustworkx, installing the python dependencies, and then building the\ndocumentation in an isolated venv. \n\nOur documentation setup requires that the [uv](https://github.com/astral-sh/uv)\nbackend for Nox is installed. That can be done with `pip install -U \"nox[uv]\"`.\n\nYou can run just the docs build with:\n```\nnox -e docs\n```\nwhich will output the html rendered documentation in `docs/build/html` which\nyou can view locally in a web browser.\n\n> [!TIP]\n> If you run `nox -e docs -- -j auto`, the documentation uses all CPUs and builds faster.\n\n#### rustworkx-core documentation\n\nTo build the rustworkx-core documentation you will use rust-doc. You can do this\nby running:\n```\ncargo doc -p rustworkx-core\n```\nAfter it's built the compiled documentation will be located in\n`target/doc/rustworkx_core` (which is off the repo root not the `rustworkx-core`\ndir)\n\nYou can build and open the documentation directly in your configured default\nweb browser by running:\n\n```\ncargo doc -p rustworkx-core --open\n```\n\n#### Updating documentation dependencies\n\nThe documentation workflow is currently our step with the most dependencies. Even\nthough `rustworkx` currently has very few Python dependencies, our documentation depends\non `sphinx` and many others. Therefore, `uv.lock` file contains a frozen list of what\ncan be used for the workflow.\n\nIf you need to add or remove dependencies, update `pyproject.toml` (specifically the `docs`\nsection in `dependency-groups`), and then run `uv sync --all-groups` to update `uv.lock`.\n\n### Type Annotations\n\nIf you have added new methods, functions, or classes, and/or changed any\nsignatures, type annotations for Python are required to be included in a pull\nrequest. Type annotations are added using type\n[stub files](https://typing.readthedocs.io/en/latest/source/stubs.html) which\nprovide type annotations to python tooling which use type annotations. The stub\nfiles are in the `rustworkx/` directory and have a `.pyi` file extension. They\ncontain annotated signatures for Python functions, stripped of their\nimplementation. You can find more details on typing in Python at:\n\n * https://mypy.readthedocs.io/en/stable/\n * https://typing.readthedocs.io/en/latest/\n * https://docs.python.org/3/library/typing.html\n\nHaving type annotations is very helpful for Python end-users. Adding\nannotations lets users type check their code with [mypy](http://mypy-lang.org/),\nwhich can be helpful for finding bugs when using rustworkx.\n\nJust like with tests for the code, annotations are also tested via Nox.\n\n```\nnox -e stubs\n```\n\nOne important thing to note is that if you're adding a new function to the Rust\nmodule you will need to ensure that the signature with annotations is added to\n`rustworkx/rustworkx.pyi`. Then it is also necessary to re-export the annotation\nby adding an import line to `rustworkx/__init__.pyi` in the form:\n\n```python\nfrom .rustworkx import foo as foo\n```\n\nwhich ensures that mypy is able to find the type annotations when users import\nfrom the root `rustworkx` package (which is the most common access pattern).\n\n### Release Notes\n\nIt is important to document any end user facing changes when we release a new\nversion of rustworkx.  The expectation is that if your code contribution has\nuser facing changes that you will write the release documentation for these\nchanges. This documentation must explain what was changed, why it was changed,\nand how users can either use or adapt to the change. The idea behind release\ndocumentation is that when a naive user with limited internal knowledge of the\nproject is upgrading from the previous release to the new one, they should be\nable to read the release notes, understand if they need to update their\nprogram which uses rustworkx, and how they would go about doing that. It\nideally should explain why they need to make this change too, to provide the\nnecessary context.\n\nTo make sure we don't forget a release note or if the details of user facing\nchanges over a release cycle we require that all user facing changes include\ndocumentation at the same time as the code. To accomplish this we use the\n[reno](https://docs.openstack.org/reno/latest/) tool which enables a git based\nworkflow for writing and compiling release notes.\n\n#### Adding a new release note\n\nMaking a new release note is quite straightforward. Ensure that you have reno\ninstalled with::\n\n    pip install -U reno\n\nOnce you have reno installed you can make a new release note by running in\nyour local repository checkout's root::\n\n    reno new short-description-string\n\nwhere short-description-string is a brief string (with no spaces) that describes\nwhat's in the release note. This will become the prefix for the release note\nfile. Once that is run it will create a new yaml file in releasenotes/notes.\nThen open that yaml file in a text editor and write the release note. The basic\nstructure of a release note is restructured text in yaml lists under category\nkeys. You add individual items under each category and they will be grouped\nautomatically by release when the release notes are compiled. A single file\ncan have as many entries in it as needed, but to avoid potential conflicts\nyou'll want to create a new file for each pull request that has user facing\nchanges. When you open the newly created file it will be a full template of\nthe different categories with a description of a category as a single entry\nin each category. You'll want to delete all the sections you aren't using and\nupdate the contents for those you are. For example, the end result should\nlook something like::\n\n```yaml\nfeatures:\n  - |\n    Added a new function, :func:`~rustworkx.foo` that adds support for doing\n    something to :class:`~rustworkx.PyDiGraph` objects.\n  - |\n    The :class:`~rustworkx.PyDiGraph` class has a new method\n    :meth:`~rustworkx.PyDiGraph.foo``. This is the equivalent of calling the\n    :func:`~rustworkx.foo` function to do something to your\n    :class:`~rustworkx.PyDiGraph` object, but provides the convenience of running\n    it natively on an object. For example::\n\n      from rustworkx import PyDiGraph\n\n      g = PyDiGraph.\n      g.foo()\n\ndeprecations:\n  - |\n    The ``rustworkx.bar`` function has been deprecated and will be removed in a\n    future release. It has been superseded by the\n    :meth:`~rustworkx.PyDiGraph.foo` method and :func:`~rustworkx.foo` function\n    which provides similar functionality but with more accurate results and\n    better performance. You should update your calls\n    ``rustworkx.bar()`` calls to use ``rustworkx.foo()`` instead.\n```\n\nYou can also look at other release notes for other examples.\n\nYou can use any\n[sphinx feature](https://www.sphinx-doc.org/en/3.x/usage/restructuredtext/)\nin them (code sections, tables, enumerated lists, bulleted list, etc) to express\nwhat is being changed as needed. In general you want the release notes to\ninclude as much detail as needed so that users will understand what has changed,\nwhy it changed, and how they'll have to update their code.\n\nAfter you've finished writing your release notes you'll want to add the note\nfile to your commit with `git add` and commit them to your PR branch to make\nsure they're included with the code in your PR.\n\n##### Linking to issues\n\nIf you need to link to an issue or other Github artifact as part of the release\nnote this should be done using an inline link with the text being the issue\nnumber. For example you would write a release note with a link to issue 12345\nas:\n\n```yaml\nfixes:\n  - |\n    Fixes a race condition in the function ``foo()``. Refer to\n    `#12345 <https://github.com/Qiskit/rustworkx/issues/12345>`__ for more\n    details.\n```\n\n#### Generating the release notes\n\nAfter release notes have been added if you want to see what the full output of\nthe release notes. Reno is used to combine the release note yaml files into a\nsingle rst (ReStructuredText) document that\n[sphinx](https://www.sphinx-doc.org/en/master/) will then compile for us as part\nof the documentation builds. If you want to generate the rst file you\nuse the ``reno report`` command. If you want to generate the full rustworkx\nrelease notes for all releases (since we started using reno during 0.8) you just\nrun::\n\n    reno report\n\nbut you can also use the ``--version`` argument to view a single release (after\nit has been tagged::\n\n    reno report --version 0.8.0\n\n#### Building release notes locally\n\nBuilding the release notes is part of the standard rustworkx documentation\nbuilds. To check what the rendered html output of the release notes will look\nlike for the current state of the repo you can run: `nox -e docs` which will\nbuild all the documentation into `docs/_build/html` and the release notes in\nparticular will be located at `docs/_build/html/release_notes.html`\n\n### Pull request review, CI, and merge queue\n\nAfter you've submitted a pull request to rustworkx it will need to pass CI and be\nreviewed by an approved by a core team reviewer. CI runs get triggered\nautomatically when your pull request is opened and on every subsequent commit\nmade to your pull request's branch. Code review however may take some time,\nsometimes even weeks or months, there are many new pull requests opened every\nday and limited number of reviewers available, and while every proposed change\nis a valuable addition to the project not everything is the highest priority.\nYou can help this process move more quickly by actively reviewing other open\nPRs. While only members of the rustworkx core team have permission to provide\nfinal approval and mark a PR as ready for merging, reviewing code is open to\neveryone and all reviews are welcome and extremely valued contributions.\nHelping with code review also helps reduce the burden on the core team and\nenables them to review code faster.\n\nThe code review process is a bit of back and forth where you will receive\nfeedback and questions about your proposed changes to the project. You will\nlikely have multiple rounds of feedback with suggestions or changes requested\nbefore approval. Please do not get discouraged as this is normal and part of\nensuring the quality of the rustworkx project and even what first appears as a\nstraightforward or simple change might have larger implications that aren't\nobvious at first. If you receive feedback feel free to request re-review from\nreviewers after you've adjusted your PR based on the comments received.\n\nAnother thing to keep in mind is that CI time is a constrained resource and not\ninfinite. While waiting for review and approval it is not necessary to keep your\nPR branch up to date on every change to the `main` branch. Doing it periodically\nis fine to make sure there are no regressions as the codebase changes, but\ndoing it too often will just needlessly waste CI resources. This will contribute\nto resource starvation on CI, slowing down total throughput for the project. If\npossible try to bundle updating your branch to the current HEAD on the `main`\nbranch with other changes made to the PR branch (like making adjustments from\ncode review). This will result in a single CI run instead of doing standalone\nupdates with no code changes.\n\nOnce your PR has the necessary approvals it will be tagged with the `automerge`\ntag. This is a signal to the [mergify bot](https://mergify.io/) that the PR has\nbeen approved and is ready for merging. The mergify bot will then enqueue the\nPR onto its merge queue. At this point the process of updating a PR to the\ncurrent HEAD of the `main` branch is fully automated and once CI passes mergify\nwill merge the PR automatically. In an effort to conserve CI resources and\nmaximize throughput the mergify bot will only update a PR when it's next in the\nmerge queue. It might appear as activity on your PR is idle at this point, but\nthis likely just means the mergify merge queue is deep and/or CI has a backlog.\nDo **not** manually update a PR branch to HEAD on the `main` branch after it\nhas the necessary approvals and is tagged as `automerge` unless it has a merge\nconflict or has a failed CI run. Doing so will just waste CI resources and\ndelay everything from merging, including your PR.\n\n### Stable Branch Policy and Backporting\n\nThe stable branch is intended to be a safe source of fixes for high-impact bugs,\ndocumentation fixes, and security issues that have been fixed on main since a\nrelease. When reviewing a stable branch PR, we must balance the risk of any given\npatch with the value that it will provide to users of the stable branch. Only a\nlimited class of changes are appropriate for inclusion on the stable branch. A\nlarge, risky patch for a major issue might make sense, as might a trivial fix\nfor a fairly obscure error-handling case. A number of factors must be weighed\nwhen considering a change:\n\n- The risk of regression: even the tiniest changes carry some risk of breaking\n  something, and we really want to avoid regressions on the stable branch.\n- The user visibility benefit: are we fixing something that users might actually\n  notice, and if so, how important is it?\n- How self-contained the fix is: if it fixes a significant issue but also\n  refactors a lot of code, it’s probably worth thinking about what a less risky\n  fix might look like.\n- Whether the fix is already on main: a change must be a backport of a change\n  already merged onto main, unless the change simply does not make sense on\n  main.\n\nNormally only bug fixes or non-code changes are allowed on a stable branch, the\nprimary exception to this is adding support for new python versions. If a new\npython version is released backporting that feature change with that new support\nis an acceptable backport.\n\nIn rustworkx at least until the 1.0 release we only maintain a single stable\nbranch at a time for the most recent minor version release.\n\n#### Backporting procedure\n\nIn the normal case to backport a pull request all that needs to be done is\nto tag it as `stable-backport-potential`, this will signal the\n[mergify bot](https://mergify.io/) that the PR should be backported after it\nmerged. Once a PR tagged as `stable-backport-potential` merges mergify will\nautomatically open a new PR backporting it to the stable branch.\n\n##### Manual backport procedure\n\nIf the mergify approach doesn't work for some reason and you need to manual\nbackport a PR this can be done with the following procedure. When backporting a\npatch from main to stable, we want to keep a reference to the change on main.\nWhen you create the branch for the stable PR, use:\n\n```\n$ git cherry-pick -x $main_commit_id\n```\n\nHowever, this only works for small self-contained patches from main. If you\nneed to backport a subset of a larger commit (from a squashed PR, for example)\nfrom main, do this manually. In these cases, add:\n\n```\nBackported from: #main pr number\n```\n\nso that we can track the source of the change subset, even if a strict\ncherry-pick doesn't make sense.\n\nIf the patch you’re proposing will not cherry-pick cleanly, you can help by\nresolving the conflicts yourself and proposing the resulting patch. Please keep\nConflicts lines in the commit message to help review of the stable patch.\n"
    },
    "has_security_md": true,
    "has_citation_cff": false,
    "has_codemeta": false
  },
  "readme_citation": {
    "found": true,
    "section_text": "## Authors and Citation\n\nrustworkx is the work of [many people](https://github.com/Qiskit/rustworkx/graphs/contributors) who contribute\nto the project at different levels. If you use rustworkx in your research, please cite our\n[paper](https://doi.org/10.21105/joss.03968) as per the included [BibTeX file](CITATION.bib).",
    "doi": "10.21105/joss.03968"
  },
  "channels": {
    "slack": [
      "https://qiskit.slack.com/messages/rustworkx/"
    ],
    "gh_pages": [
      "https://rust-lang.github.io/rfcs/2495-min-rust-version.html",
      "https://python-pillow.github.io/"
    ]
  },
  "registries": [],
  "ground_truth": {
    "project": "rustworkx",
    "repo": "Qiskit/rustworkx",
    "current_version": {
      "value": "0.18.0",
      "source": "github_release|cff|codemeta|pypi",
      "verified": false
    },
    "maintainers": {
      "value": [
        "Qiskit"
      ],
      "source": "cff_authors|codemeta_authors|github_owner",
      "verified": false
    },
    "official_channels": {
      "value": {
        "slack": [
          "https://qiskit.slack.com/messages/rustworkx/"
        ],
        "gh_pages": [
          "https://rust-lang.github.io/rfcs/2495-min-rust-version.html",
          "https://python-pillow.github.io/"
        ]
      },
      "source": "readme/homepage_scan",
      "verified": false
    },
    "security_reporting": {
      "value": "SECURITY.md present",
      "source": "github_security_md",
      "verified": false
    },
    "citation_doi": {
      "value": null,
      "source": "cff_doi|preferred_citation_doi|zenodo_conceptdoi",
      "verified": false
    },
    "homepage": {
      "value": "https://www.rustworkx.org",
      "source": "github_homepage",
      "verified": false
    },
    "_needs_human_verification": [
      "current_version",
      "maintainers",
      "official_channels",
      "security_reporting",
      "citation_doi",
      "homepage"
    ]
  }
}